filehasher/__init__.py
filehasher/__main__.py
filehasher/cmdline.py
filehasher/version.py
filehasher-1.0.2.dist-info/METADATA
filehasher-1.0.2.dist-info/WHEEL
filehasher-1.0.2.dist-info/entry_points.txt
filehasher-1.0.2.dist-info/top_level.txt
filehasher-1.0.2.dist-info/zip-safe
filehasher-1.0.2.dist-info/RECORD
