Metadata-Version: 2.4
Name: filehasher
Version: 1.0.2
Summary: Modern file hashing utility with parallel processing, multiple algorithms, and benchmarking
Home-page: http://github.com/cyberplant/filehasher
Author: Luar Roji
Author-email: cyberplant@roji.net
License: MIT
Keywords: filehasher,file,hasher,hash,benchmark,dupe,duplicate
Classifier: Development Status :: 5 - Production/Stable
Classifier: Operating System :: OS Independent
Classifier: Programming Language :: Python :: 3
Classifier: Programming Language :: Python :: 3.8
Classifier: Programming Language :: Python :: 3.9
Classifier: Programming Language :: Python :: 3.10
Classifier: Programming Language :: Python :: 3.11
Classifier: Programming Language :: Python :: 3.12
Classifier: Topic :: Software Development :: Libraries :: Python Modules
Classifier: Topic :: System :: Filesystems
Classifier: Topic :: Utilities
Classifier: Topic :: System :: Archiving
Classifier: License :: OSI Approved :: MIT License
Requires-Dist: tqdm>=4.0.0
Requires-Dist: rich>=10.0.0
Dynamic: author
Dynamic: author-email
Dynamic: classifier
Dynamic: home-page
Dynamic: keywords
Dynamic: license
Dynamic: requires-dist
Dynamic: summary
